MANIFEST.in
setup.cfg
setup.py
velo/__init__.py
velo.egg-info/PKG-INFO
velo.egg-info/SOURCES.txt
velo.egg-info/dependency_links.txt
velo.egg-info/entry_points.txt
velo.egg-info/requires.txt
velo.egg-info/top_level.txt
velo/model/__init__.py
velo/static/bootstrap/css/bootstrap-responsive.css
velo/static/bootstrap/css/bootstrap-responsive.min.css
velo/static/bootstrap/css/bootstrap.css
velo/static/bootstrap/css/bootstrap.min.css
velo/static/bootstrap/img/glyphicons-halflings-white.png
velo/static/bootstrap/img/glyphicons-halflings.png
velo/static/bootstrap/js/bootstrap.js
velo/static/bootstrap/js/bootstrap.min.js
velo/templates/base.mako
velo/templates/index.mako
velo/views/__init__.py