Metadata-Version: 1.0
Name: velo
Version: 0.0.0
Summary: Velobstacles RESTful webapp
Home-page: UNKNOWN
Author: Hadrien David
Author-email: hadrien@ectobal.com
License: UNKNOWN
Platform: UNKNOWN
